Metadata-Version: 2.1
Name: BinaryVectorDB
Version: 0.0.2
Summary: Efficient vector DB using binary & int8 embeddings
Home-page: https://github.com/cohere-ai/BinaryVectorDB
Author: Nils Reimers
Author-email: nils@cohere.com
License: Apache License 2.0
Download-URL: https://github.com/cohere-ai/BinaryVectorDB/archive/v0.0.1.zip
Keywords: Vector Database
Platform: UNKNOWN
Classifier: Development Status :: 4 - Beta
Classifier: Intended Audience :: Science/Research
Classifier: License :: OSI Approved :: Apache Software License
Classifier: Programming Language :: Python :: 3.9
Classifier: Topic :: Scientific/Engineering :: Artificial Intelligence
License-File: LICENSE
